bracketdot/__init__.py
bracketdot/android.py
bracketdot/command_line.py
bracketdot/gitdiff.py
bracketdot/ios.py
bracketdot/spell_check.py
bracketdot/svndiff.py
bracketdot-1.0.1.dist-info/LICENSE
bracketdot-1.0.1.dist-info/METADATA
bracketdot-1.0.1.dist-info/WHEEL
bracketdot-1.0.1.dist-info/entry_points.txt
bracketdot-1.0.1.dist-info/top_level.txt
bracketdot-1.0.1.dist-info/RECORD
