Metadata-Version: 2.1
Name: bracketdot
Version: 1.0.1
Summary: A tool that runs lint focusing only on the latest changes in Git.
Home-page: https://github.com/shotaIDE/BracketDot
Author: Shota Ide
License: MIT
Keywords: development lint git
Platform: UNKNOWN
Classifier: Development Status :: 3 - Alpha
Classifier: Intended Audience :: Developers
Classifier: Topic :: Software Development :: Build Tools
Classifier: License :: OSI Approved :: MIT License
Classifier: Programming Language :: Python :: 3.6
Classifier: Programming Language :: Python :: 3.7
Requires-Python: ~=3.6
Requires-Dist: pyspellchecker (>=0.4.0)
Provides-Extra: dev
Requires-Dist: pytest ; extra == 'dev'
Requires-Dist: pytest-cov ; extra == 'dev'
Requires-Dist: pytest-pycodestyle ; extra == 'dev'
